_czifile.cp37-win_amd64.pyd
workjets/__init__.py
workjets/cmdColor.py
workjets/bunch/__init__.py
workjets/bunch/test.py
workjets/czifile/__init__.py
workjets/czifile/core.py
workjets/torchloss/__init__.py
workjets/torchloss/loss.py
workjets/torchnets/__init__.py
workjets/torchnets/RAUnet3D/RAUnet3D.py
workjets/torchnets/RAUnet3D/__init__.py
workjets/torchnets/Unet3D/__init__.py
workjets/torchnets/Unet3D/buildingblocks.py
workjets/torchnets/Unet3D/unet3d.py
workjets/torchnets/Unet3D/utils.py
workjets-0.1.6.data/data/libCZI.dll
workjets-0.1.6.dist-info/LICENSE
workjets-0.1.6.dist-info/METADATA
workjets-0.1.6.dist-info/WHEEL
workjets-0.1.6.dist-info/top_level.txt
workjets-0.1.6.dist-info/RECORD
